Async_Animanga
