Metadata-Version: 2.1
Name: Async-Animanga
Version: 0.9.5
Summary: Async-Animanga, meant for Python. It scrapes the web for information about Manga, Anime and Doujin. (Hentai/Ecchi Anime not supported yet) It uses a modern Pythonic API and advanced aiohttp/asyncio implementations to provide extreme performance upgrades for large scale projects.
Home-page: UNKNOWN
Author: TheOnlyWayUp
Author-email: thedarkdraconian@gmail.com
License: UNKNOWN
Keywords: async,aiohttp,better_than_sync,anime,manga,web scraping,hentai,doujin
Platform: UNKNOWN
Classifier: Development Status :: 5 - Production/Stable
Classifier: Intended Audience :: Developers
Classifier: Programming Language :: Python :: 3
Classifier: Operating System :: Unix
Classifier: Operating System :: MacOS :: MacOS X
Classifier: Operating System :: Microsoft :: Windows
